postroj/__init__.py
postroj/api.py
postroj/cli.py
postroj/container.py
postroj/exceptions.py
postroj/image.py
postroj/model.py
postroj/pkgprobe.py
postroj/probe.py
postroj/registry.py
postroj/runner.py
postroj/selftest.py
postroj/settings.py
postroj/util.py
postroj/winrunner.py
postroj/backend/__init__.py
postroj/backend/nspawn.py
racker/__init__.py
racker/babelfish.py
racker/cli.py
racker/image.py
testing/__init__.py
testing/conftest.py
testing/util.py
testing/postroj/__init__.py
testing/postroj/test_images.py
testing/postroj/test_pkgprobe.py
testing/postroj/test_selftest.py
testing/postroj/test_util.py
testing/racker/__init__.py
testing/racker/test_run.py
racker-0.3.0.dist-info/LICENSE
racker-0.3.0.dist-info/METADATA
racker-0.3.0.dist-info/WHEEL
racker-0.3.0.dist-info/entry_points.txt
racker-0.3.0.dist-info/top_level.txt
racker-0.3.0.dist-info/RECORD
