Metadata-Version: 2.1
Name: racker
Version: 0.3.0
Summary: Racker is an experimental harness tool for provisioning and launching operating system containers
Home-page: https://github.com/cicerops/racker
Download-URL: https://pypi.org/project/racker/
Author: Andreas Motl
Author-email: andreas.motl@cicerops.de
License: AGPL-3.0, EUPL-1.2
Keywords: systemd,systemd-nspawn,systemd-container,systemd-run,machinectl,virtual,environment,build,test,testing,test-harness,harness-framework,test-environment,testing-tool,harness,oci,oci-image,oci-images,virtualbox,vagrant,docker,docker-image,skopeo,umoci
Classifier: Programming Language :: Python
Classifier: Programming Language :: Python :: 3
Classifier: License :: OSI Approved :: GNU Affero General Public License v3
Classifier: License :: OSI Approved :: European Union Public Licence 1.2 (EUPL 1.2)
Classifier: Development Status :: 3 - Alpha
Classifier: Operating System :: POSIX :: Linux
Classifier: Natural Language :: English
Classifier: Intended Audience :: Customer Service
Classifier: Intended Audience :: Developers
Classifier: Intended Audience :: Education
Classifier: Intended Audience :: Information Technology
Classifier: Intended Audience :: Manufacturing
Classifier: Intended Audience :: Science/Research
Classifier: Intended Audience :: System Administrators
Classifier: Intended Audience :: Telecommunications Industry
Classifier: Topic :: Communications
Classifier: Topic :: Education :: Testing
Classifier: Topic :: Software Development :: Build Tools
Classifier: Topic :: Software Development :: Libraries
Classifier: Topic :: Software Development :: Quality Assurance
Classifier: Topic :: Software Development :: Testing
Classifier: Topic :: Scientific/Engineering
Classifier: Topic :: System :: Emulators
Classifier: Topic :: System :: Networking
Classifier: Topic :: Utilities
License-File: LICENSE
Requires-Dist: click (<9,>=7)
Requires-Dist: furl (<3,>=2)
Requires-Dist: subprocess-tee (<1,>=0.3)
Requires-Dist: python-slugify (<7,>=6)
Requires-Dist: tld (<1,>=0.10)
Provides-Extra: release
Requires-Dist: build (<1) ; extra == 'release'
Requires-Dist: twine (<5) ; extra == 'release'
Provides-Extra: test
Requires-Dist: pytest (<8,>=6) ; extra == 'test'
Requires-Dist: pytest-cov (<3,>=2) ; extra == 'test'
Requires-Dist: re-assert (<2,>=1) ; extra == 'test'
